nexor/__init__.py
nexor/__main__.py
nexor/depend.py
nexor/env.py
nexor/lock.py
nexor/tests/__init__.py
nexor/tests/test_init.py
nexor-2024.1.19.65996.dist-info/METADATA
nexor-2024.1.19.65996.dist-info/WHEEL
nexor-2024.1.19.65996.dist-info/entry_points.txt
nexor-2024.1.19.65996.dist-info/top_level.txt
nexor-2024.1.19.65996.dist-info/RECORD
