Metadata-Version: 2.1
Name: nexor
Version: 2024.1.19.65996
Summary: A Python tooling nexus
Author-email: Moshe Zadka <moshez@zadka.club>
License: Permission is hereby granted, free of charge, to any person obtaining a
Project-URL: Homepage, https://github.com/moshez/nexor
Requires-Dist: gather
Requires-Dist: tomlkit
Requires-Dist: pip-tools
Requires-Dist: commander-data
Provides-Extra: docs
Requires-Dist: sphinx ; extra == 'docs'
Provides-Extra: lint
Requires-Dist: flake8 ; extra == 'lint'
Requires-Dist: black ; extra == 'lint'
Provides-Extra: mypy
Requires-Dist: mypy ; extra == 'mypy'
Provides-Extra: tests
Requires-Dist: virtue ; extra == 'tests'
Requires-Dist: pyhamcrest ; extra == 'tests'
Requires-Dist: coverage ; extra == 'tests'
